tests/__init__.py
tests/alexa_test.py
tests/opendns_test.py
tests/virustotal_test.py
tests/util/__init__.py
tests/util/api_cache_test.py
tests/util/error_messages_test.py
tests/util/http_test.py
threat_intel/__init__.py
threat_intel/alexaranking.py
threat_intel/exceptions.py
threat_intel/help.py
threat_intel/opendns.py
threat_intel/shadowserver.py
threat_intel/virustotal.py
threat_intel/util/__init__.py
threat_intel/util/api_cache.py
threat_intel/util/error_messages.py
threat_intel/util/http.py
threat_intel/util/http2.py
threat_intel-0.1.27.dist-info/DESCRIPTION.rst
threat_intel-0.1.27.dist-info/METADATA
threat_intel-0.1.27.dist-info/RECORD
threat_intel-0.1.27.dist-info/WHEEL
threat_intel-0.1.27.dist-info/metadata.json
threat_intel-0.1.27.dist-info/top_level.txt
